[
  {
    "row": 1,
    "rowsha": "47DEQpj8HBSa+/TImW+5JCeuQeRkm5NMpJWZG3hSuFU=",
    "originContent": "",
    "translatedContent": ""
  },
  {
    "row": 2,
    "rowsha": "cWgam+tnnXudu7i74+ahMEGk/A9dQS+EwWLAIfi3dHk=",
    "originContent": "<div align=\"right\">",
    "translatedContent": "<div align=\"right\">"
  },
  {
    "row": 3,
    "rowsha": "orOcu5ARna/hb3RUkj6dBI8pHTM3WHeTvby17l5E0h0=",
    "originContent": "  <details>",
    "translatedContent": "  <details>"
  },
  {
    "row": 4,
    "rowsha": "TtgkLzblnvP0q9aAIVXt6s2LczXjy5k+QvHKcU0/5Ms=",
    "originContent": "    <summary >🌐 Language</summary>",
    "translatedContent": "    <summary >🌐 ভাষা</summary>"
  },
  {
    "row": 5,
    "rowsha": "fZtk4rPTAJEEslnbhSVkHEcPlsctYSzAV7CDPL3rJmA=",
    "originContent": "    <div>",
    "translatedContent": "    <div>"
  },
  {
    "row": 6,
    "rowsha": "9KQxOeJSigvTmGWO+mtnl8kZY9zQfueoy8sk4lYm09Q=",
    "originContent": "      <div align=\"center\">",
    "translatedContent": "      <div align=\"center\">"
  },
  {
    "row": 7,
    "rowsha": "QUw+f/nT+QBKH5t3mrdj8Mzz3J7ImXuBtWDBVxQuLl4=",
    "originContent": "        <a href=\"https://openaitx.github.io/view.html?user=babluboy&project=nutty&lang=en\">English</a>",
    "translatedContent": "        <a href=\"https://openaitx.github.io/view.html?user=babluboy&project=nutty&lang=en\">ইংৰাজী</a>"
  },
  {
    "row": 8,
    "rowsha": "Kcepma4yAk+0s7eBZDVDV0ro1YAvTmizjaJX0xMRCKY=",
    "originContent": "        | <a href=\"https://openaitx.github.io/view.html?user=babluboy&project=nutty&lang=zh-CN\">简体中文</a>",
    "translatedContent": "        | <a href=\"https://openaitx.github.io/view.html?user=babluboy&project=nutty&lang=zh-CN\">সৰল চাইনীজ</a>"
  },
  {
    "row": 9,
    "rowsha": "WGdwQK/DOx2eEJpYgwAFsh+7GozM2QNFhoqmh7AfrDE=",
    "originContent": "        | <a href=\"https://openaitx.github.io/view.html?user=babluboy&project=nutty&lang=zh-TW\">繁體中文</a>",
    "translatedContent": "        | <a href=\"https://openaitx.github.io/view.html?user=babluboy&project=nutty&lang=zh-TW\">পৰম্পৰাগত চাইনীজ</a>"
  },
  {
    "row": 10,
    "rowsha": "qFyEUZ7+9n7MIiUhYuERePuFRhP6q1YDwO+rGjTk2z8=",
    "originContent": "        | <a href=\"https://openaitx.github.io/view.html?user=babluboy&project=nutty&lang=ja\">日本語</a>",
    "translatedContent": "        | <a href=\"https://openaitx.github.io/view.html?user=babluboy&project=nutty&lang=ja\">জাপানী</a>"
  },
  {
    "row": 11,
    "rowsha": "UsLqkNv0VT67kBBl6bgjzbosFXUDGh4j/4jfbqN5T/o=",
    "originContent": "        | <a href=\"https://openaitx.github.io/view.html?user=babluboy&project=nutty&lang=ko\">한국어</a>",
    "translatedContent": "        | <a href=\"https://openaitx.github.io/view.html?user=babluboy&project=nutty&lang=ko\">কোৰিয়ান</a>"
  },
  {
    "row": 12,
    "rowsha": "Y64prWkGm5/23iXZjkVFhzfxoVRN+ZaIyp8qdujlVjc=",
    "originContent": "        | <a href=\"https://openaitx.github.io/view.html?user=babluboy&project=nutty&lang=hi\">हिन्दी</a>",
    "translatedContent": "        | <a href=\"https://openaitx.github.io/view.html?user=babluboy&project=nutty&lang=hi\">হিন্দী</a>"
  },
  {
    "row": 13,
    "rowsha": "B3VikDJSjapMJgIXfnbcvFemQ4Vdonm0dskqfCpYxtU=",
    "originContent": "        | <a href=\"https://openaitx.github.io/view.html?user=babluboy&project=nutty&lang=th\">ไทย</a>",
    "translatedContent": "        | <a href=\"https://openaitx.github.io/view.html?user=babluboy&project=nutty&lang=th\">থাই</a>"
  },
  {
    "row": 14,
    "rowsha": "RgHRLCFawku3kpBXpSGJtAtcVlBqZowMrfT2TLcmIKg=",
    "originContent": "        | <a href=\"https://openaitx.github.io/view.html?user=babluboy&project=nutty&lang=fr\">Français</a>",
    "translatedContent": "        | <a href=\"https://openaitx.github.io/view.html?user=babluboy&project=nutty&lang=fr\">ফ্ৰেঞ্চ</a>"
  },
  {
    "row": 15,
    "rowsha": "wdRHo0cKnVCdG6PAeXsVWjj6JJAun4k1YnMu+HuhhGk=",
    "originContent": "        | <a href=\"https://openaitx.github.io/view.html?user=babluboy&project=nutty&lang=de\">Deutsch</a>",
    "translatedContent": "        | <a href=\"https://openaitx.github.io/view.html?user=babluboy&project=nutty&lang=de\">জাৰ্মান</a>"
  },
  {
    "row": 16,
    "rowsha": "dAyQP8jTYA4ImzX8fbFeSA1zaGYcys5Ca5p+4vx3EoU=",
    "originContent": "        | <a href=\"https://openaitx.github.io/view.html?user=babluboy&project=nutty&lang=es\">Español</a>",
    "translatedContent": "        | <a href=\"https://openaitx.github.io/view.html?user=babluboy&project=nutty&lang=es\">স্পেনী</a>"
  },
  {
    "row": 17,
    "rowsha": "p5VbqxKli+T3278JCXe7Zf9tob0uG9MVp3faFQZZatc=",
    "originContent": "        | <a href=\"https://openaitx.github.io/view.html?user=babluboy&project=nutty&lang=it\">Italiano</a>",
    "translatedContent": "        | <a href=\"https://openaitx.github.io/view.html?user=babluboy&project=nutty&lang=it\">ইটালীয়ান</a>"
  },
  {
    "row": 18,
    "rowsha": "o7SgeKX9//J4oKq7gpn20QGxFcgrBzdel2QpMRXsQCY=",
    "originContent": "        | <a href=\"https://openaitx.github.io/view.html?user=babluboy&project=nutty&lang=ru\">Русский</a>",
    "translatedContent": "        | <a href=\"https://openaitx.github.io/view.html?user=babluboy&project=nutty&lang=ru\">ৰাছিয়ান</a>"
  },
  {
    "row": 19,
    "rowsha": "k2F8hJ7Xw5PxwdmPUNhUongdX5+FWDA2esR0YGTQhqo=",
    "originContent": "        | <a href=\"https://openaitx.github.io/view.html?user=babluboy&project=nutty&lang=pt\">Português</a>",
    "translatedContent": "        | <a href=\"https://openaitx.github.io/view.html?user=babluboy&project=nutty&lang=pt\">পৰ্তুগীজ</a>"
  },
  {
    "row": 20,
    "rowsha": "y48njbW0+dXw0sW19xtotw5aN7P7oTyzK4KDAGF5br0=",
    "originContent": "        | <a href=\"https://openaitx.github.io/view.html?user=babluboy&project=nutty&lang=nl\">Nederlands</a>",
    "translatedContent": "        | <a href=\"https://openaitx.github.io/view.html?user=babluboy&project=nutty&lang=nl\">ডাচ</a>"
  },
  {
    "row": 21,
    "rowsha": "hjfxT3DkhZXVfSE3Q1qLvguYwb7B+H6z0YpqrDh6nKg=",
    "originContent": "        | <a href=\"https://openaitx.github.io/view.html?user=babluboy&project=nutty&lang=pl\">Polski</a>",
    "translatedContent": "        | <a href=\"https://openaitx.github.io/view.html?user=babluboy&project=nutty&lang=pl\">প'লিছ</a>"
  },
  {
    "row": 22,
    "rowsha": "OtZlb3uEN9Ym30QtXtwxzvPbYYWjX3SCUGCVyKICbv4=",
    "originContent": "        | <a href=\"https://openaitx.github.io/view.html?user=babluboy&project=nutty&lang=ar\">العربية</a>",
    "translatedContent": "        | <a href=\"https://openaitx.github.io/view.html?user=babluboy&project=nutty&lang=ar\">আৰবী</a>"
  },
  {
    "row": 23,
    "rowsha": "+V4obPu00Fampp4KUb/0Lih1jvjS1dzpGdPLFf+7fqc=",
    "originContent": "        | <a href=\"https://openaitx.github.io/view.html?user=babluboy&project=nutty&lang=fa\">فارسی</a>",
    "translatedContent": "        | <a href=\"https://openaitx.github.io/view.html?user=babluboy&project=nutty&lang=fa\">ফাৰ্ছী</a>"
  },
  {
    "row": 24,
    "rowsha": "mzP+N52UzSegUwLGRilLRSUhj2Ym3qIDmZrw6mKOcSU=",
    "originContent": "        | <a href=\"https://openaitx.github.io/view.html?user=babluboy&project=nutty&lang=tr\">Türkçe</a>",
    "translatedContent": "        | <a href=\"https://openaitx.github.io/view.html?user=babluboy&project=nutty&lang=tr\">টাৰ্কী</a>"
  },
  {
    "row": 25,
    "rowsha": "qi/nHLdFb3+8mHXx+daZZY0WMKs6uqqQrEVjdTbCz2o=",
    "originContent": "        | <a href=\"https://openaitx.github.io/view.html?user=babluboy&project=nutty&lang=vi\">Tiếng Việt</a>",
    "translatedContent": "        | <a href=\"https://openaitx.github.io/view.html?user=babluboy&project=nutty&lang=vi\">ভিয়েতনামী</a>"
  },
  {
    "row": 26,
    "rowsha": "ziqbbUtpA/DNSwX5S6/F4wppLG1vTo9VdVquIE3dx2U=",
    "originContent": "        | <a href=\"https://openaitx.github.io/view.html?user=babluboy&project=nutty&lang=id\">Bahasa Indonesia</a>",
    "translatedContent": "        | <a href=\"https://openaitx.github.io/view.html?user=babluboy&project=nutty&lang=id\">ইন্দোনেশীয়</a>"
  },
  {
    "row": 27,
    "rowsha": "+akSZl1nl9mFTRgLA1alKKnT5k49ZXkUPJ2SI0p1RfE=",
    "originContent": "        | <a href=\"https://openaitx.github.io/view.html?user=babluboy&project=nutty&lang=as\">অসমীয়া</",
    "translatedContent": "        | <a href=\"https://openaitx.github.io/view.html?user=babluboy&project=nutty&lang=as\">অসমীয়া</"
  },
  {
    "row": 28,
    "rowsha": "0OM5wNEm0TO56MEBvQzL7AUZM7/3OpgIeqRf2zFre3Q=",
    "originContent": "      </div>",
    "translatedContent": "      </div>"
  },
  {
    "row": 29,
    "rowsha": "fcjTfY+fs8YnY5slBs1sZvWPAqEQR7tzaBDO54skkGQ=",
    "originContent": "    </div>",
    "translatedContent": "    </div>"
  },
  {
    "row": 30,
    "rowsha": "+fQNH2ldI7UM/rqRscP3hUSWAmw1HvQ2wEKDN8JagT0=",
    "originContent": "  </details>",
    "translatedContent": "  </details>"
  },
  {
    "row": 31,
    "rowsha": "qsMmUbEPVnxGG5tPJV1vsfpoWbU2jYvZpRr5IKshzyM=",
    "originContent": "</div>",
    "translatedContent": "</div>"
  },
  {
    "row": 32,
    "rowsha": "47DEQpj8HBSa+/TImW+5JCeuQeRkm5NMpJWZG3hSuFU=",
    "originContent": "",
    "translatedContent": ""
  },
  {
    "row": 33,
    "rowsha": "5nC4KqU42IJyS7FyTt4co6+BGGR7gH4CcvBE+fLE+8U=",
    "originContent": "# Nutty [![Translation status](https://hosted.weblate.org/widgets/nutty/-/svg-badge.svg)](https://hosted.weblate.org/engage/nutty/?utm_source=widget) [![Build Status](https://travis-ci.org/babluboy/nutty.svg?branch=master)](https://travis-ci.org/babluboy/nutty) [![Snap Status](https://build.snapcraft.io/badge/babluboy/nutty.svg)](https://build.snapcraft.io/user/babluboy/nutty) [![Donate](https://img.shields.io/badge/Donate-PayPal-green.svg)](https://www.paypal.com/cgi-bin/webscr?cmd=_s-xclick&hosted_button_id=FZP8GK839VGQC)",
    "translatedContent": "# Nutty [![Translation status](https://hosted.weblate.org/widgets/nutty/-/svg-badge.svg)](https://hosted.weblate.org/engage/nutty/?utm_source=widget) [![Build Status](https://travis-ci.org/babluboy/nutty.svg?branch=master)](https://travis-ci.org/babluboy/nutty) [![Snap Status](https://build.snapcraft.io/badge/babluboy/nutty.svg)](https://build.snapcraft.io/user/babluboy/nutty) [![Donate](https://img.shields.io/badge/Donate-PayPal-green.svg)](https://www.paypal.com/cgi-bin/webscr?cmd=_s-xclick&hosted_button_id=FZP8GK839VGQC)"
  },
  {
    "row": 34,
    "rowsha": "5u0Wezxj7EOWyyGYE0iMlU7fRwgkKFnN7MDyuS+CcVY=",
    "originContent": "A Network Utility",
    "translatedContent": "এখন নেটৱৰ্ক ইউটিলিটি"
  },
  {
    "row": 35,
    "rowsha": "47DEQpj8HBSa+/TImW+5JCeuQeRkm5NMpJWZG3hSuFU=",
    "originContent": "",
    "translatedContent": ""
  },
  {
    "row": 36,
    "rowsha": "vmoj0cLSrDvcprfv/gvIZB5XJFqQiQO2QdrpqViNR6Y=",
    "originContent": "Author: Siddhartha Das",
    "translatedContent": "লেখক: সিদ্ধার্থ দাস"
  },
  {
    "row": 37,
    "rowsha": "47DEQpj8HBSa+/TImW+5JCeuQeRkm5NMpJWZG3hSuFU=",
    "originContent": "",
    "translatedContent": ""
  },
  {
    "row": 38,
    "rowsha": "LQPDk7kdqrYDq46w2aF2qU4YGvzRq2VCEXW8jba07U4=",
    "originContent": "A simple application made for elementary OS to provide essential information on network related aspects. The information presented in as the following tabs.<br>",
    "translatedContent": "elementary OS ৰ বাবে তৈয়াৰ কৰা এটা সাধাৰণ এপ্লিকেশ্যন যি নেটৱৰ্ক সম্পৰ্কীয় বিষয়সমূহৰ প্ৰয়োজনীয় তথ্য প্ৰদান কৰে। তথ্যসমূহ তলত উল্লেখ কৰা ট্যাবসমূহত দেখুওৱা হৈছে।<br>"
  },
  {
    "row": 39,
    "rowsha": "941cKpjj+2pj2rLbPD+8wQ+vrUWVnrP0c9rEqKX/i40=",
    "originContent": "1. My Info: Provides basic and detailed information for the device network card<br>",
    "translatedContent": "১. My Info: ডিভাইচৰ নেটৱৰ্ক কাৰ্ডৰ মৌলিক আৰু বিস্তৃত তথ্য প্ৰদান কৰে<br>"
  },
  {
    "row": 40,
    "rowsha": "JSi8peFD/grY4nJAe3D9ai2XKgZYkuj02s7R+FbXpXs=",
    "originContent": "2. Usage: Provides network data usage in two views - historical usage and current usage<br>",
    "translatedContent": "২. Usage: নেটৱৰ্ক ডেটা ব্যৱহাৰ দুটা দৃশ্যত দেখুৱায় - ইতিবৃত্তমূলক ব্যৱহাৰ আৰু বৰ্তমান ব্যৱহাৰ<br>"
  },
  {
    "row": 41,
    "rowsha": "YePuGz5HZY8Y9fjqgKPcuxz5xdnvRmGrw1fVYxtXKV8=",
    "originContent": "3. Speed: Check Upload and Download speeds and get route times to a host<br>",
    "translatedContent": "৩. গতি: আপল'ড আৰু ডাউনল'ড গতিবিধি পৰীক্ষা কৰক আৰু কোনো হষ্টলৈ ৰুট সময় জানক<br>"
  },
  {
    "row": 42,
    "rowsha": "JUbX+PivYmGL6W3YJjDOkYGybze3QR0Fr127LaTGjQk=",
    "originContent": "4. Ports: Provides information on active ports and application using them on the local device<br>",
    "translatedContent": "৪. পোৰ্টছ: সক্ৰিয় পোৰ্ট আৰু স্থানীয় ডিভাইচত সিহঁত ব্যৱহাৰ কৰা এপ্লিকেশ্যনসমূহৰ বিষয়ে তথ্য দিয়ে<br>"
  },
  {
    "row": 43,
    "rowsha": "fQl2lZM/dUiN5GtTXwpIAPRkBG3D+nOWtD3/cz5X6Ak=",
    "originContent": "5. Devices: Monitors, alerts and provides information on the other devices connected on the network<br>",
    "translatedContent": "৫. ডিভাইচসমূহ: নেটৱৰ্কত সংযুক্ত অন্য ডিভাইচসমূহ মনিটৰ, এলাৰ্ট আৰু তথ্য প্ৰদান কৰে<br>"
  },
  {
    "row": 44,
    "rowsha": "47DEQpj8HBSa+/TImW+5JCeuQeRkm5NMpJWZG3hSuFU=",
    "originContent": "",
    "translatedContent": ""
  },
  {
    "row": 45,
    "rowsha": "uV9efTu4bdRb2WSif8eYW/DMEGSwLz1KshEwB2gJdaQ=",
    "originContent": "Check the Nutty website for details on features, shortcuts, installation guides for Ubuntu and other supported distros, etc. : <br>",
    "translatedContent": "বিৱৰণ, চমু পথ, উবুন্টু আৰু অন্যান্য সমৰ্থিত ডিষ্ট্ৰোৰ ইনষ্টলেচন গাইড আদিৰ বাবে Nutty ৱেবছাইট চাওক : <br>"
  },
  {
    "row": 46,
    "rowsha": "y4mc9tjTP2vYcpskGRGY/hV3bc0h4n5WUC8NfF848Vg=",
    "originContent": "https://babluboy.github.io/nutty/",
    "translatedContent": "https://babluboy.github.io/nutty/"
  },
  {
    "row": 47,
    "rowsha": "47DEQpj8HBSa+/TImW+5JCeuQeRkm5NMpJWZG3hSuFU=",
    "originContent": "",
    "translatedContent": ""
  },
  {
    "row": 48,
    "rowsha": "/vCpQPfsODjRaDkL5HRFwy1DrwdZ6tWuwaPkkHPi0qU=",
    "originContent": "## Building, Testing, and Installation from Source",
    "translatedContent": "## উৎসৰ পৰা নিৰ্মাণ, পৰীক্ষা আৰু ইনষ্টলেচন"
  },
  {
    "row": 49,
    "rowsha": "47DEQpj8HBSa+/TImW+5JCeuQeRkm5NMpJWZG3hSuFU=",
    "originContent": "",
    "translatedContent": ""
  },
  {
    "row": 50,
    "rowsha": "nrGZNZyEyohRwTUBnC2mVl7V0W68OGind9utO1X8UKA=",
    "originContent": "You'll need the following dependencies to build:",
    "translatedContent": "নিৰ্মাণৰ বাবে তলত দিয়া নিৰ্ভৰশীলতাসমূহৰ প্ৰয়োজন:"
  },
  {
    "row": 51,
    "rowsha": "Z0ZJPZtlfmSvBHqwl5zpZ/XanhjFGDUX9DE7tqiBCsc=",
    "originContent": "* libgranite-dev",
    "translatedContent": "* libgranite-dev"
  },
  {
    "row": 52,
    "rowsha": "wISIJRGIYYfk5LVd/lhy/sBgaZhCAfyPUwN/MODDyHc=",
    "originContent": "* libnotify-dev",
    "translatedContent": "* libnotify-dev"
  },
  {
    "row": 53,
    "rowsha": "1A8TiU0lSQqRlJ8GVwOGrFKJEiarQ7GLxoEROXgFtKw=",
    "originContent": "* libxml2-dev",
    "translatedContent": "* libxml2-dev"
  },
  {
    "row": 54,
    "rowsha": "Lcg0Qq/MN5xReby4eLE5p1TtjiRmT3VM29wg/eYMkfw=",
    "originContent": "* libxml2-utils",
    "translatedContent": "* libxml2-utils"
  },
  {
    "row": 55,
    "rowsha": "Gg0absJuJenMpxtHsFOWLo8KGa4gU/ba0QHLd/oJvgU=",
    "originContent": "* libgee-0.8-dev",
    "translatedContent": "* libgee-0.8-dev"
  },
  {
    "row": 56,
    "rowsha": "JseBjL8clYczdkAUON9jYQQIOagqy8tQYtQceUESi1U=",
    "originContent": "* libgtk-3-dev",
    "translatedContent": "* libgtk-3-dev"
  },
  {
    "row": 57,
    "rowsha": "2BUDr5+EybWuXciItgm6T4soIJuZsa6WAkILiUJn5Fo=",
    "originContent": "* libsqlite3-dev",
    "translatedContent": "* libsqlite3-dev"
  },
  {
    "row": 58,
    "rowsha": "pyu3mZkbswlGVvDZNun27oHHBOrCGbN6SGvO8tsJCRE=",
    "originContent": "* meson",
    "translatedContent": "* meson"
  },
  {
    "row": 59,
    "rowsha": "6JiZupfTf0YAnTQQ7p+1RmTko6yoTXQ4N5wJWPgY19E=",
    "originContent": "* valac",
    "translatedContent": "* valac"
  },
  {
    "row": 60,
    "rowsha": "47DEQpj8HBSa+/TImW+5JCeuQeRkm5NMpJWZG3hSuFU=",
    "originContent": "",
    "translatedContent": ""
  },
  {
    "row": 61,
    "rowsha": "bO/C9sgvd96/fF6/aSOQCoGBZ88CR1kMwB5pl4LuZUY=",
    "originContent": "And these dependencies to execute:",
    "translatedContent": "চলাবলৈ এই নিৰ্ভৰশীলতাসমূহৰ প্ৰয়োজন:"
  },
  {
    "row": 62,
    "rowsha": "lCuKLeBXRpRXqU2v/k7myOHDFgVmfXhMlYgH3Q6o3gc=",
    "originContent": "* net-tools",
    "translatedContent": "* net-tools"
  },
  {
    "row": 63,
    "rowsha": "PL+kgFPlc2/MC0KKF8IlvgLDHIwaIxTTZt7bSu8C2xY=",
    "originContent": "* nethogs",
    "translatedContent": "* nethogs"
  },
  {
    "row": 64,
    "rowsha": "z9F6+F9sJJTCuf4D/zTSL2N0PW/l5vJJGpTk8qmggVc=",
    "originContent": "* nmap",
    "translatedContent": "* nmap"
  },
  {
    "row": 65,
    "rowsha": "XgpA7XAGHt1qZJgbzmtYkLeCD8wZXst/QoCYP87y89c=",
    "originContent": "* traceroute",
    "translatedContent": "* traceroute"
  },
  {
    "row": 66,
    "rowsha": "FaQSEJDOK9CX0mjCLZKkxd5Qko+H8FkqyoeI/TXNCB4=",
    "originContent": "* vnstat",
    "translatedContent": "* vnstat"
  },
  {
    "row": 67,
    "rowsha": "n5ZMDRMjAn2jUdqfgymWQp2nvNEJ+qVUtGyxvane/Hw=",
    "originContent": "* curl",
    "translatedContent": "* curl"
  },
  {
    "row": 68,
    "rowsha": "qqzFHFmb2cVQCckebt2yw7Lch05Gulfno5dmPlfUKOU=",
    "originContent": "* wireless-tools",
    "translatedContent": "* wireless-tools"
  },
  {
    "row": 69,
    "rowsha": "r+xOZtNoVP6XwXLD5XprOHKqunvntaLySgNoBv2RVXQ=",
    "originContent": "* iproute2",
    "translatedContent": "* iproute2"
  },
  {
    "row": 70,
    "rowsha": "z6QSdKA0NXalMeO2EroQLGofN6RX+xfCWGqPyS/ta+U=",
    "originContent": "* pciutils",
    "translatedContent": "* pciutils"
  },
  {
    "row": 71,
    "rowsha": "47DEQpj8HBSa+/TImW+5JCeuQeRkm5NMpJWZG3hSuFU=",
    "originContent": "",
    "translatedContent": ""
  },
  {
    "row": 72,
    "rowsha": "nADxgVUpuQglYAYhFE5gIdZ5Cwk8HQUyws9GM1nwQ7o=",
    "originContent": "Sometimes vnstat is not started upon install, use the appropriate init system command to start vnstat daemon i.e. `sudo systemctl enable vnstat`",
    "translatedContent": "কেতিয়াবা vnstat ইনষ্টল কৰাৰ পিছত আৰম্ভ নহয়, vnstat ডিমন আৰম্ভ কৰিবলৈ উপযুক্ত init system কমাণ্ড ব্যৱহাৰ কৰক, যেনে `sudo systemctl enable vnstat`"
  },
  {
    "row": 73,
    "rowsha": "47DEQpj8HBSa+/TImW+5JCeuQeRkm5NMpJWZG3hSuFU=",
    "originContent": "",
    "translatedContent": ""
  },
  {
    "row": 74,
    "rowsha": "B4UfCgnOSjTSb1FGcaog05Ju46ypG42DXyfET+H3bRM=",
    "originContent": "Run `meson build` to configure the build environment and run `ninja test` to build",
    "translatedContent": "নিৰ্মাণ পৰিৱেশ কনফিগাৰ কৰিবলৈ `meson build` চলাওক আৰু নিৰ্মাণ কৰিবলৈ `ninja test` চলাওক"
  },
  {
    "row": 75,
    "rowsha": "47DEQpj8HBSa+/TImW+5JCeuQeRkm5NMpJWZG3hSuFU=",
    "originContent": "",
    "translatedContent": ""
  },
  {
    "row": 76,
    "rowsha": "8bkBhHOQsO1+N058HkZOwXtGpCfEh6WtbL0pBkBQg9U=",
    "originContent": "```",
    "translatedContent": "```"
  },
  {
    "row": 77,
    "rowsha": "gxmKacpGu505XdTEXh9FrQZaXfyrVT9/Jbi2Sd7kt1M=",
    "originContent": "git clone https://github.com/babluboy/nutty.git",
    "translatedContent": "git clone https://github.com/babluboy/nutty.git"
  },
  {
    "row": 78,
    "rowsha": "KpwA73GBGZ83DCqpbAEQO3HR4jQd9kJ5UwOtCQjC6wo=",
    "originContent": "cd nutty",
    "translatedContent": "cd nutty"
  },
  {
    "row": 79,
    "rowsha": "RUYBkf9FQ9g/sMa7Xfi7uPN9PZL5LsIOlcXjvfN1kQU=",
    "originContent": "meson build --prefix=/usr",
    "translatedContent": "meson build --prefix=/usr"
  },
  {
    "row": 80,
    "rowsha": "2E91V0MAwN4o4nI9U0XkQPFhdwGamzSnsb7s2xe+3Uw=",
    "originContent": "cd build",
    "translatedContent": "cd build"
  },
  {
    "row": 81,
    "rowsha": "VEgllRdxFuYQOwdtvzBkjl0FN90e2c9a5FYvqKcA1Hs=",
    "originContent": "ninja",
    "translatedContent": "ninja"
  },
  {
    "row": 82,
    "rowsha": "8bkBhHOQsO1+N058HkZOwXtGpCfEh6WtbL0pBkBQg9U=",
    "originContent": "```",
    "translatedContent": "```"
  },
  {
    "row": 83,
    "rowsha": "47DEQpj8HBSa+/TImW+5JCeuQeRkm5NMpJWZG3hSuFU=",
    "originContent": "",
    "translatedContent": "ইন্সটল কৰিবলৈ, `sudo ninja install` ব্যৱহাৰ কৰক, তাৰ পাছত `com.github.babluboy.nutty` দ্বাৰা এক্সিকিউট কৰক"
  },
  {
    "row": 84,
    "rowsha": "Nf+PD5wl1M47y3q4MEktKbQFOfmshdlrfORrNR6Hxcg=",
    "originContent": "To install, use `sudo ninja install`, then execute with `com.github.babluboy.nutty`",
    "translatedContent": ""
  },
  {
    "row": 85,
    "rowsha": "47DEQpj8HBSa+/TImW+5JCeuQeRkm5NMpJWZG3hSuFU=",
    "originContent": "",
    "translatedContent": ""
  },
  {
    "row": 86,
    "rowsha": "8bkBhHOQsO1+N058HkZOwXtGpCfEh6WtbL0pBkBQg9U=",
    "originContent": "```",
    "translatedContent": "```"
  },
  {
    "row": 87,
    "rowsha": "/LSDjI/rKuyWW1JSEuwDi3IxTWhm0Y8eHo/5AKu38oc=",
    "originContent": "sudo ninja install",
    "translatedContent": "sudo ninja install"
  },
  {
    "row": 88,
    "rowsha": "zt4+zyg8U5jM+QuSlqOjSI+KrNjjTCE2JdDCe+8nb9k=",
    "originContent": "com.github.babluboy.nutty",
    "translatedContent": "com.github.babluboy.nutty"
  },
  {
    "row": 89,
    "rowsha": "8bkBhHOQsO1+N058HkZOwXtGpCfEh6WtbL0pBkBQg9U=",
    "originContent": "```",
    "translatedContent": "```"
  },
  {
    "row": 90,
    "rowsha": "47DEQpj8HBSa+/TImW+5JCeuQeRkm5NMpJWZG3hSuFU=",
    "originContent": "",
    "translatedContent": "অনইনষ্টল কৰিবলৈ, বিল্ড ডাইৰেক্টৰীত যাওক আৰু চলাও"
  },
  {
    "row": 91,
    "rowsha": "zBKQdpBV7f7xcqO8t+XPiqjAVs1pwtCR+AuOJ3bD2RE=",
    "originContent": "To uninstall ,go to the build directory and run",
    "translatedContent": ""
  },
  {
    "row": 92,
    "rowsha": "8bkBhHOQsO1+N058HkZOwXtGpCfEh6WtbL0pBkBQg9U=",
    "originContent": "```",
    "translatedContent": "```"
  },
  {
    "row": 93,
    "rowsha": "qZWQZu9/a79LaIs7lBds4Rasta6c5Sjlh/wJZ2EyXLg=",
    "originContent": "sudo ninja uninstall",
    "translatedContent": "sudo ninja uninstall"
  },
  {
    "row": 94,
    "rowsha": "8bkBhHOQsO1+N058HkZOwXtGpCfEh6WtbL0pBkBQg9U=",
    "originContent": "```",
    "translatedContent": "```"
  },
  {
    "row": 95,
    "rowsha": "47DEQpj8HBSa+/TImW+5JCeuQeRkm5NMpJWZG3hSuFU=",
    "originContent": "",
    "translatedContent": ""
  },
  {
    "row": 96,
    "rowsha": "5K6vwJaLfHjBBRO4UYh2PbuZ0m1XlwNslpZq0z9OkGo=",
    "originContent": "### Installation from Deb package",
    "translatedContent": "### ডেব পেকেজৰ পৰা ইনষ্টলেশন"
  },
  {
    "row": 97,
    "rowsha": "47DEQpj8HBSa+/TImW+5JCeuQeRkm5NMpJWZG3hSuFU=",
    "originContent": "",
    "translatedContent": ""
  },
  {
    "row": 98,
    "rowsha": "df5NOIzcO5fnjJAO7HvRpnA+b/ZiKVAbTM/1LwNSdAE=",
    "originContent": "To install Nutty from the `.deb` package make sure you have installed all the above execution dependencies of Nutty (no need build dependencies). Then run the below command",
    "translatedContent": "`.deb` পেকেজৰ পৰা Nutty ইনষ্টল কৰিবলৈ, নিশ্চিত কৰক যে আপুনি Nutty-ৰ ওপৰৰ সকলো এক্সিকিউশন ডিপেণ্ডেন্সী ইনষ্টল কৰিছে (বিল্ড ডিপেণ্ডেন্সী লাগিব নালাগে)। তাৰ পিছত তলৰ নিৰ্দেশটো চলাও"
  },
  {
    "row": 99,
    "rowsha": "rTMjNc+qNIxb1xXDR5hEYiJw1fc4muBwuBsTXVIaIho=",
    "originContent": "```bash",
    "translatedContent": "```bash"
  },
  {
    "row": 100,
    "rowsha": "FTMX+70/NfS1Zsky0E7zXe7IvBEiHQLfDwHGK4i4nPg=",
    "originContent": "sudo dpkg -i <deb-package-name>.deb",
    "translatedContent": "sudo dpkg -i <deb-package-name>.deb"
  },
  {
    "row": 101,
    "rowsha": "8bkBhHOQsO1+N058HkZOwXtGpCfEh6WtbL0pBkBQg9U=",
    "originContent": "```",
    "translatedContent": "```"
  },
  {
    "row": 102,
    "rowsha": "47DEQpj8HBSa+/TImW+5JCeuQeRkm5NMpJWZG3hSuFU=",
    "originContent": "",
    "translatedContent": ""
  },
  {
    "row": 103,
    "rowsha": "ZBk+2DbcLCv0pPXAiBW0TAw3xYKOhpLwYRbYcD07G0o=",
    "originContent": "And to uninstall Nutty installed via `.deb` package run",
    "translatedContent": "আৰু `.deb` পেকেজৰ জৰিয়তে সংস্থাপন কৰা Nutty আনইনষ্টল কৰিবলৈ এইটো চলাও"
  },
  {
    "row": 104,
    "rowsha": "rTMjNc+qNIxb1xXDR5hEYiJw1fc4muBwuBsTXVIaIho=",
    "originContent": "```bash",
    "translatedContent": "```bash"
  },
  {
    "row": 105,
    "rowsha": "ZLgxh04GN9VnqBlfvcZLuSrljwGSydH6zea/Ri5vRdA=",
    "originContent": "sudo apt autoremove com.github.babluboy.nutty",
    "translatedContent": "sudo apt autoremove com.github.babluboy.nutty"
  },
  {
    "row": 106,
    "rowsha": "8bkBhHOQsO1+N058HkZOwXtGpCfEh6WtbL0pBkBQg9U=",
    "originContent": "```",
    "translatedContent": "```"
  },
  {
    "row": 107,
    "rowsha": "47DEQpj8HBSa+/TImW+5JCeuQeRkm5NMpJWZG3hSuFU=",
    "originContent": "",
    "translatedContent": "আপুনি যদি Nutty-ৰ `.deb` পেকেজটো নিজে সৰ্বসাক্ষাৎকৈ বনাব খুজে, তেন্তে ওপৰৰ নিৰ্মাণ নিৰ্ভৰশীলসমূহ ইনষ্টল কৰক আৰু তাৰ পিছত চলাও"
  },
  {
    "row": 108,
    "rowsha": "xUn5LQ5PocOP1Kx0XsjN+wP35Y0QdYFqVfcURTTzuwU=",
    "originContent": "If you want to directly build the `.deb` package of Nutty yourself then install the above build dependencies and then run",
    "translatedContent": ""
  },
  {
    "row": 109,
    "rowsha": "rTMjNc+qNIxb1xXDR5hEYiJw1fc4muBwuBsTXVIaIho=",
    "originContent": "```bash",
    "translatedContent": "```bash"
  },
  {
    "row": 110,
    "rowsha": "gxmKacpGu505XdTEXh9FrQZaXfyrVT9/Jbi2Sd7kt1M=",
    "originContent": "git clone https://github.com/babluboy/nutty.git",
    "translatedContent": "git clone https://github.com/babluboy/nutty.git"
  },
  {
    "row": 111,
    "rowsha": "KpwA73GBGZ83DCqpbAEQO3HR4jQd9kJ5UwOtCQjC6wo=",
    "originContent": "cd nutty",
    "translatedContent": "cd nutty"
  },
  {
    "row": 112,
    "rowsha": "IgglyHmRLxvxBBky0TirhNYVl2RB9lKsd6WdouPVGFk=",
    "originContent": "dpkg-buildpackage -us -uc",
    "translatedContent": "dpkg-buildpackage -us -uc"
  },
  {
    "row": 113,
    "rowsha": "7MeL2ie4MsaVajW98e6Pt1n4VCWp6MhdKO21I7tnefU=",
    "originContent": "cd ..",
    "translatedContent": "cd .."
  },
  {
    "row": 114,
    "rowsha": "8bkBhHOQsO1+N058HkZOwXtGpCfEh6WtbL0pBkBQg9U=",
    "originContent": "```",
    "translatedContent": "```"
  },
  {
    "row": 115,
    "rowsha": "47DEQpj8HBSa+/TImW+5JCeuQeRkm5NMpJWZG3hSuFU=",
    "originContent": "",
    "translatedContent": ""
  },
  {
    "row": 116,
    "rowsha": "47DEQpj8HBSa+/TImW+5JCeuQeRkm5NMpJWZG3hSuFU=",
    "originContent": "",
    "translatedContent": ""
  },
  {
    "row": 117,
    "rowsha": "//9AuIIaXy9mvaAGc/r6mkESt/laTi9ivwat9mNHcs0=",
    "originContent": "## Screenshot",
    "translatedContent": "## Screenshot"
  },
  {
    "row": 118,
    "rowsha": "47DEQpj8HBSa+/TImW+5JCeuQeRkm5NMpJWZG3hSuFU=",
    "originContent": "",
    "translatedContent": ""
  },
  {
    "row": 119,
    "rowsha": "T6QiOlzKnQexr09ztk6Ji50wTeo+U+jHCZqhDZZZ/aE=",
    "originContent": "![screenshot](https://raw.githubusercontent.com/babluboy/nutty/gh-pages/images/Nutty_Device_Alert.png)",
    "translatedContent": "![screenshot](https://raw.githubusercontent.com/babluboy/nutty/gh-pages/images/Nutty_Device_Alert.png)"
  },
  {
    "row": 120,
    "rowsha": "47DEQpj8HBSa+/TImW+5JCeuQeRkm5NMpJWZG3hSuFU=",
    "originContent": "",
    "translatedContent": ""
  }
]