[
  {
    "row": 1,
    "rowsha": "M/J5lGcXcoeikmB4ChB6yY6mPdYWX2f8wNdHZ9CoIJA=",
    "originContent": "<p>",
    "translatedContent": "<p>"
  },
  {
    "row": 2,
    "rowsha": "MM+z6VEvjmBtbGEhWjxVTw38Pu5G5aO5nJUCOXgWklY=",
    "originContent": "  <div align=\"center\">",
    "translatedContent": "  <div align=\"center\">"
  },
  {
    "row": 3,
    "rowsha": "eZZG+Cwc4Sq3uGJiPxEp0TBCjHGq6IPOw4GBfPw95tQ=",
    "originContent": "  <h1>",
    "translatedContent": "  <h1>"
  },
  {
    "row": 4,
    "rowsha": "q9rWy7aiyvBmIfos2YghD3d2WF52jFnEdr55Edmf4Ts=",
    "originContent": "    Snapchat Public Stories Downloader<br /> <br />",
    "translatedContent": "    Descargador de Historias Públicas de Snapchat<br /> <br />"
  },
  {
    "row": 5,
    "rowsha": "frRZKq4BsY5Zix9yxgKtfBRChWVnWFz5vuDFmcPjP/I=",
    "originContent": "    <a href=\"https://pypi.python.org/pypi/snapchat-dl\">",
    "translatedContent": "    <a href=\"https://pypi.python.org/pypi/snapchat-dl\">"
  },
  {
    "row": 6,
    "rowsha": "lpVVi0rj7X00Y/3z1vZt5TiCxCVlv1099iKilkfgfw4=",
    "originContent": "      <img",
    "translatedContent": "      <img"
  },
  {
    "row": 7,
    "rowsha": "ocgItj2HsRpnaJyWKiVe6uRxC4aAqXmpLPyCO19xyVc=",
    "originContent": "        src=\"https://img.shields.io/pypi/v/snapchat-dl.svg?cacheSeconds=360\"",
    "translatedContent": "        src=\"https://img.shields.io/pypi/v/snapchat-dl.svg?cacheSeconds=360\""
  },
  {
    "row": 8,
    "rowsha": "hcS0if8fcjwpNgoQu6zlZgfR31tuuUfDuAVD1WlCohw=",
    "originContent": "        alt=\"Python Package\"",
    "translatedContent": "        alt=\"Paquete de Python\""
  },
  {
    "row": 9,
    "rowsha": "5wp2GBwQoHZoG0b0x7DA8igs4rjwg5du1U92ZziR368=",
    "originContent": "      />",
    "translatedContent": "      />"
  },
  {
    "row": 10,
    "rowsha": "r52QjIbZf1aIcwCydWRFx1LDX4Vc0bsXMVxnkEUrqHA=",
    "originContent": "    </a>",
    "translatedContent": "    </a>"
  },
  {
    "row": 11,
    "rowsha": "frRZKq4BsY5Zix9yxgKtfBRChWVnWFz5vuDFmcPjP/I=",
    "originContent": "    <a href=\"https://pypi.python.org/pypi/snapchat-dl\">",
    "translatedContent": "    <a href=\"https://pypi.python.org/pypi/snapchat-dl\">"
  },
  {
    "row": 12,
    "rowsha": "lpVVi0rj7X00Y/3z1vZt5TiCxCVlv1099iKilkfgfw4=",
    "originContent": "      <img",
    "translatedContent": "      <img"
  },
  {
    "row": 13,
    "rowsha": "AcrELIWwVBGbw18OL0yuoUF1fwFFlqa9qwX/4HNGWrE=",
    "originContent": "        src=\"https://img.shields.io/pypi/wheel/snapchat-dl\"",
    "translatedContent": "        src=\"https://img.shields.io/pypi/wheel/snapchat-dl\""
  },
  {
    "row": 14,
    "rowsha": "gbB0VzdeNMCcIEHKEsMCgFN+r3mkZN07f3V84Zm0w4k=",
    "originContent": "        alt=\"Python Wheel\"",
    "translatedContent": "        alt=\"Rueda de Python\""
  },
  {
    "row": 15,
    "rowsha": "5wp2GBwQoHZoG0b0x7DA8igs4rjwg5du1U92ZziR368=",
    "originContent": "      />",
    "translatedContent": "      />"
  },
  {
    "row": 16,
    "rowsha": "r52QjIbZf1aIcwCydWRFx1LDX4Vc0bsXMVxnkEUrqHA=",
    "originContent": "    </a>",
    "translatedContent": "    </a>"
  },
  {
    "row": 17,
    "rowsha": "frRZKq4BsY5Zix9yxgKtfBRChWVnWFz5vuDFmcPjP/I=",
    "originContent": "    <a href=\"https://pypi.python.org/pypi/snapchat-dl\">",
    "translatedContent": "    <a href=\"https://pypi.python.org/pypi/snapchat-dl\">"
  },
  {
    "row": 18,
    "rowsha": "lpVVi0rj7X00Y/3z1vZt5TiCxCVlv1099iKilkfgfw4=",
    "originContent": "      <img",
    "translatedContent": "      <img"
  },
  {
    "row": 19,
    "rowsha": "TklW/VGfqP96sqKIwdGgrSs4KP3vOk6EQ8kR1w9sSTA=",
    "originContent": "        src=\"https://img.shields.io/github/actions/workflow/status/skyme5/snapchat-dl/continuous-integration-pip.yml?cacheSeconds=360\"",
    "translatedContent": "        src=\"https://img.shields.io/github/actions/workflow/status/skyme5/snapchat-dl/continuous-integration-pip.yml?cacheSeconds=360\""
  },
  {
    "row": 20,
    "rowsha": "PXWBYL7krlFhfUuW9GPtkhbyyD7SS1/sfz4oCWV4xPA=",
    "originContent": "        alt=\"CI\"",
    "translatedContent": "        alt=\"CI\""
  },
  {
    "row": 21,
    "rowsha": "5wp2GBwQoHZoG0b0x7DA8igs4rjwg5du1U92ZziR368=",
    "originContent": "      />",
    "translatedContent": "      />"
  },
  {
    "row": 22,
    "rowsha": "r52QjIbZf1aIcwCydWRFx1LDX4Vc0bsXMVxnkEUrqHA=",
    "originContent": "    </a>",
    "translatedContent": "    </a>"
  },
  {
    "row": 23,
    "rowsha": "6qfnb45XnnklUmDZLPESmvdW92hjgCz6R77oN2Ue6cY=",
    "originContent": "    <a href=\"https://codecov.io/gh/skyme5/snapchat-dl\">",
    "translatedContent": "    <a href=\"https://codecov.io/gh/skyme5/snapchat-dl\">"
  },
  {
    "row": 24,
    "rowsha": "lpVVi0rj7X00Y/3z1vZt5TiCxCVlv1099iKilkfgfw4=",
    "originContent": "      <img",
    "translatedContent": "      <img"
  },
  {
    "row": 25,
    "rowsha": "gG6NDnjXmAijrO+vfkH1Bd9ENs/YMUiSanHuFUTwiYc=",
    "originContent": "        src=\"https://img.shields.io/codecov/c/github/skyme5/snapchat-dl?cacheSeconds=360\"",
    "translatedContent": "        src=\"https://img.shields.io/codecov/c/github/skyme5/snapchat-dl?cacheSeconds=360\""
  },
  {
    "row": 26,
    "rowsha": "IszDnc20vlIvKnzgl5Gf5a66/gNDjxEoaZpZZRsgrp4=",
    "originContent": "        alt=\"Code Coverage\"",
    "translatedContent": "        alt=\"Cobertura de Código\""
  },
  {
    "row": 27,
    "rowsha": "5wp2GBwQoHZoG0b0x7DA8igs4rjwg5du1U92ZziR368=",
    "originContent": "      />",
    "translatedContent": "      />"
  },
  {
    "row": 28,
    "rowsha": "r52QjIbZf1aIcwCydWRFx1LDX4Vc0bsXMVxnkEUrqHA=",
    "originContent": "    </a>",
    "translatedContent": "    </a>"
  },
  {
    "row": 29,
    "rowsha": "6qfnb45XnnklUmDZLPESmvdW92hjgCz6R77oN2Ue6cY=",
    "originContent": "    <a href=\"https://codecov.io/gh/skyme5/snapchat-dl\">",
    "translatedContent": "    <a href=\"https://codecov.io/gh/skyme5/snapchat-dl\">"
  },
  {
    "row": 30,
    "rowsha": "lpVVi0rj7X00Y/3z1vZt5TiCxCVlv1099iKilkfgfw4=",
    "originContent": "      <img",
    "translatedContent": "      <img"
  },
  {
    "row": 31,
    "rowsha": "GSXD+53/AjTjDBvFz3/gq7UJLQu43Xq//yWH06aA9lE=",
    "originContent": "        src=\"https://img.shields.io/pypi/pyversions/snapchat-dl\"",
    "translatedContent": "        src=\"https://img.shields.io/pypi/pyversions/snapchat-dl\""
  },
  {
    "row": 32,
    "rowsha": "qCn5oy2S9K0mzTOueOZy5p04c9Ih23fz5jyTdo1o6fQ=",
    "originContent": "        alt=\"Python Versions\"",
    "translatedContent": "        alt=\"Versiones de Python\""
  },
  {
    "row": 33,
    "rowsha": "5wp2GBwQoHZoG0b0x7DA8igs4rjwg5du1U92ZziR368=",
    "originContent": "      />",
    "translatedContent": "      />"
  },
  {
    "row": 34,
    "rowsha": "r52QjIbZf1aIcwCydWRFx1LDX4Vc0bsXMVxnkEUrqHA=",
    "originContent": "    </a>",
    "translatedContent": "    </a>"
  },
  {
    "row": 35,
    "rowsha": "Nvh70Lt3ZpO8yiEXFrs2alg1aNJXsumZixJTlPvvDgg=",
    "originContent": "    <a href=\"https://github.com/psf/black\">",
    "translatedContent": "    <a href=\"https://github.com/psf/black\">"
  },
  {
    "row": 36,
    "rowsha": "lpVVi0rj7X00Y/3z1vZt5TiCxCVlv1099iKilkfgfw4=",
    "originContent": "      <img",
    "translatedContent": "      <img"
  },
  {
    "row": 37,
    "rowsha": "DeXdllYfQa6a6OATcKfN7VQ9spBxH5kWKRPtEV9RZ5w=",
    "originContent": "        src=\"https://img.shields.io/badge/code%20style-black-000000.svg\"",
    "translatedContent": "        src=\"https://img.shields.io/badge/code%20style-black-000000.svg\""
  },
  {
    "row": 38,
    "rowsha": "53TePg9LZP5CfkdDSgZN713J2Fc+A9EAp4SVM9kYvkg=",
    "originContent": "        alt=\"The Uncompromising Code Formatter\"",
    "translatedContent": "        alt=\"El Formateador de Código Intransigente\""
  },
  {
    "row": 39,
    "rowsha": "5wp2GBwQoHZoG0b0x7DA8igs4rjwg5du1U92ZziR368=",
    "originContent": "      />",
    "translatedContent": "      />"
  },
  {
    "row": 40,
    "rowsha": "r52QjIbZf1aIcwCydWRFx1LDX4Vc0bsXMVxnkEUrqHA=",
    "originContent": "    </a>",
    "translatedContent": "    </a>"
  },
  {
    "row": 41,
    "rowsha": "icpPBFVQNytQyPv8bMFPza6xRLYjrYKseFdRylzS9KI=",
    "originContent": "    <a href=\"https://pepy.tech/project/snapchat-dl\">",
    "translatedContent": "    <a href=\"https://pepy.tech/project/snapchat-dl\">"
  },
  {
    "row": 42,
    "rowsha": "lpVVi0rj7X00Y/3z1vZt5TiCxCVlv1099iKilkfgfw4=",
    "originContent": "      <img",
    "translatedContent": "      <img"
  },
  {
    "row": 43,
    "rowsha": "jUm4BWieui5c8vRq7L8GsTg5hHVKytrqJeZCRda+0d8=",
    "originContent": "        src=\"https://static.pepy.tech/badge/snapchat-dl\"",
    "translatedContent": "        src=\"https://static.pepy.tech/badge/snapchat-dl\""
  },
  {
    "row": 44,
    "rowsha": "V8tDOOCVgAJ0o85pzH0xx4lqFrr1+yRrfdsAsJwV++8=",
    "originContent": "        alt=\"Monthly Downloads\"",
    "translatedContent": "        alt=\"Descargas Mensuales\""
  },
  {
    "row": 45,
    "rowsha": "5wp2GBwQoHZoG0b0x7DA8igs4rjwg5du1U92ZziR368=",
    "originContent": "      />",
    "translatedContent": "      />"
  },
  {
    "row": 46,
    "rowsha": "r52QjIbZf1aIcwCydWRFx1LDX4Vc0bsXMVxnkEUrqHA=",
    "originContent": "    </a>",
    "translatedContent": "    </a>"
  },
  {
    "row": 47,
    "rowsha": "hkUgsLfl9jgqf+8/lyvbfQxoienWZUGFBnAJF4AcSeo=",
    "originContent": "    <a href=\"https://opensource.org/licenses/MIT\">",
    "translatedContent": "    <a href=\"https://opensource.org/licenses/MIT\">"
  },
  {
    "row": 48,
    "rowsha": "lpVVi0rj7X00Y/3z1vZt5TiCxCVlv1099iKilkfgfw4=",
    "originContent": "      <img",
    "translatedContent": "      <img"
  },
  {
    "row": 49,
    "rowsha": "vEm9RR3J5lh2OHLGpFhKvJzcCrMlzN3vc9f3gNqLYPo=",
    "originContent": "        src=\"https://img.shields.io/badge/License-MIT-blue.svg\"",
    "translatedContent": "        src=\"https://img.shields.io/badge/License-MIT-blue.svg\""
  },
  {
    "row": 50,
    "rowsha": "c0/cvBVxwBBapp5o17RKawfptMCPmp0ZUfGxZ7s+NRM=",
    "originContent": "        alt=\"License: MIT\"",
    "translatedContent": "        alt=\"Licencia: MIT\""
  },
  {
    "row": 51,
    "rowsha": "5wp2GBwQoHZoG0b0x7DA8igs4rjwg5du1U92ZziR368=",
    "originContent": "      />",
    "translatedContent": "      />"
  },
  {
    "row": 52,
    "rowsha": "r52QjIbZf1aIcwCydWRFx1LDX4Vc0bsXMVxnkEUrqHA=",
    "originContent": "    </a>",
    "translatedContent": "    </a>"
  },
  {
    "row": 53,
    "rowsha": "t0/OoxAVpApiUWk6H33woGe390eMrT/LoxK1fDQZpWY=",
    "originContent": "  </h1>",
    "translatedContent": "  </h1>"
  },
  {
    "row": 54,
    "rowsha": "o1ZmwQ3Hu4An8KwKb9Owxq9vvP1xFAxDBn/vyfNqWws=",
    "originContent": "  <a href=\"https://buymeacoffee.com/skyme5\" target=\"_blank\"><img src=\"https://www.buymeacoffee.com/assets/img/custom_images/orange_img.png\" alt=\"Buy Me A Coffee\" style=\"height: 41px !important;width: 174px !important;\" ></a>",
    "translatedContent": "  <a href=\"https://buymeacoffee.com/skyme5\" target=\"_blank\"><img src=\"https://www.buymeacoffee.com/assets/img/custom_images/orange_img.png\" alt=\"Cómprame un café\" style=\"height: 41px !important;width: 174px !important;\" ></a>"
  },
  {
    "row": 55,
    "rowsha": "TFeor9sDM2gZqn6BBqB9bb7gMaKqgk0Ph1pgaT3gpaM=",
    "originContent": "  </div>",
    "translatedContent": "  </div>"
  },
  {
    "row": 56,
    "rowsha": "dSdvPNAZSmR86FDDSF6tkQUCVfI9qmACHOR5tThOetY=",
    "originContent": "</p>",
    "translatedContent": "</p>"
  },
  {
    "row": 57,
    "rowsha": "47DEQpj8HBSa+/TImW+5JCeuQeRkm5NMpJWZG3hSuFU=",
    "originContent": "",
    "translatedContent": ""
  },
  {
    "row": 58,
    "rowsha": "JuAC4s82hMbNkRqX17s0ltqjVmeI/HhsmWljgf+i7Kg=",
    "originContent": "### Installation",
    "translatedContent": "### Instalación"
  },
  {
    "row": 59,
    "rowsha": "47DEQpj8HBSa+/TImW+5JCeuQeRkm5NMpJWZG3hSuFU=",
    "originContent": "",
    "translatedContent": ""
  },
  {
    "row": 60,
    "rowsha": "Ho98xwcyf51xAAuGOB+Oba7AAyC2o7ZVzFosHxBCR9M=",
    "originContent": "Install using pip,",
    "translatedContent": "Instale usando pip,"
  },
  {
    "row": 61,
    "rowsha": "47DEQpj8HBSa+/TImW+5JCeuQeRkm5NMpJWZG3hSuFU=",
    "originContent": "",
    "translatedContent": ""
  },
  {
    "row": 62,
    "rowsha": "rTMjNc+qNIxb1xXDR5hEYiJw1fc4muBwuBsTXVIaIho=",
    "originContent": "```bash",
    "translatedContent": "```bash"
  },
  {
    "row": 63,
    "rowsha": "2UtXoGaSO3AePCAQduCls6FIgb77hK6+U8MJ7PsGWuw=",
    "originContent": "pip install snapchat-dl",
    "translatedContent": "pip install snapchat-dl"
  },
  {
    "row": 64,
    "rowsha": "8bkBhHOQsO1+N058HkZOwXtGpCfEh6WtbL0pBkBQg9U=",
    "originContent": "```",
    "translatedContent": "```"
  },
  {
    "row": 65,
    "rowsha": "47DEQpj8HBSa+/TImW+5JCeuQeRkm5NMpJWZG3hSuFU=",
    "originContent": "",
    "translatedContent": ""
  },
  {
    "row": 66,
    "rowsha": "pFPi/nrw8HC0WqpqA6cc7i83XWp5nylWbEm0QQHMzlU=",
    "originContent": "Install from GitHub,",
    "translatedContent": "Instalar desde GitHub,"
  },
  {
    "row": 67,
    "rowsha": "47DEQpj8HBSa+/TImW+5JCeuQeRkm5NMpJWZG3hSuFU=",
    "originContent": "",
    "translatedContent": ""
  },
  {
    "row": 68,
    "rowsha": "rTMjNc+qNIxb1xXDR5hEYiJw1fc4muBwuBsTXVIaIho=",
    "originContent": "```bash",
    "translatedContent": "```bash"
  },
  {
    "row": 69,
    "rowsha": "iWl1cjdpMM+LwREPXx0S/9w91l+1FB81P/9ft02nur8=",
    "originContent": "pip install git+git://github.com/skyme5/snapchat-dl",
    "translatedContent": "pip install git+git://github.com/skyme5/snapchat-dl"
  },
  {
    "row": 70,
    "rowsha": "8bkBhHOQsO1+N058HkZOwXtGpCfEh6WtbL0pBkBQg9U=",
    "originContent": "```",
    "translatedContent": "```"
  },
  {
    "row": 71,
    "rowsha": "47DEQpj8HBSa+/TImW+5JCeuQeRkm5NMpJWZG3hSuFU=",
    "originContent": "",
    "translatedContent": ""
  },
  {
    "row": 72,
    "rowsha": "BqeJ0YkLXJ56CFcxwZmwvzOe/H6lTt5wfQLfnD3TgNc=",
    "originContent": "Unix users might want to add `--user` flag to install without requiring `sudo`.",
    "translatedContent": "Los usuarios de Unix podrían querer añadir la opción `--user` para instalar sin requerir `sudo`."
  },
  {
    "row": 73,
    "rowsha": "47DEQpj8HBSa+/TImW+5JCeuQeRkm5NMpJWZG3hSuFU=",
    "originContent": "",
    "translatedContent": ""
  },
  {
    "row": 74,
    "rowsha": "elsthwRCF+vtpOBxqAWFEGuucFIX2nKj7DKSYQAuFv8=",
    "originContent": "### Usage",
    "translatedContent": "### Uso"
  },
  {
    "row": 75,
    "rowsha": "47DEQpj8HBSa+/TImW+5JCeuQeRkm5NMpJWZG3hSuFU=",
    "originContent": "",
    "translatedContent": ""
  },
  {
    "row": 76,
    "rowsha": "tKMTeRwfvKLBQQ0dWxGQr0CHcj7BtsHEundimNbdYig=",
    "originContent": "```text",
    "translatedContent": "```text"
  },
  {
    "row": 77,
    "rowsha": "47DEQpj8HBSa+/TImW+5JCeuQeRkm5NMpJWZG3hSuFU=",
    "originContent": "",
    "translatedContent": ""
  },
  {
    "row": 78,
    "rowsha": "uyLwDbf0y0F2l7TH07iyUaPvcx/DZDFIbMYT5AuFHfA=",
    "originContent": "usage: snapchat-dl [-h] [-c | -u] [-i BATCH_FILENAME] [-P DIRECTORY_PREFIX]",
    "translatedContent": "usage: snapchat-dl [-h] [-c | -u] [-i BATCH_FILENAME] [-P DIRECTORY_PREFIX]"
  },
  {
    "row": 79,
    "rowsha": "8cv8Bw6vA39eTl7jaS2TSy4NvDUG1Xc6H4kJxTOio7U=",
    "originContent": "                   [-s] [-d] [-l MAX_NUM_STORY] [-j MAX_WORKERS] [-t INTERVAL]",
    "translatedContent": "                   [-s] [-d] [-l MAX_NUM_STORY] [-j MAX_WORKERS] [-t INTERVAL]"
  },
  {
    "row": 80,
    "rowsha": "DVB/IvxTkZOlmPyXthddt4/BvlRX6wUl4R575/py7Tw=",
    "originContent": "                   [--sleep-interval INTERVAL] [-q]",
    "translatedContent": "                   [--sleep-interval INTERVAL] [-q]"
  },
  {
    "row": 81,
    "rowsha": "gdG0CMraggBcDjhvuH9twf8lQQyyw5B31/dtnJK4570=",
    "originContent": "                   [username [username ...]]",
    "translatedContent": "                   [username [username ...]]"
  },
  {
    "row": 82,
    "rowsha": "47DEQpj8HBSa+/TImW+5JCeuQeRkm5NMpJWZG3hSuFU=",
    "originContent": "",
    "translatedContent": ""
  },
  {
    "row": 83,
    "rowsha": "GrDHfJnEgQJVyPzomW5CpYeIaEQ0qO894Tu4h4G1XxE=",
    "originContent": "positional arguments:",
    "translatedContent": "positional arguments:"
  },
  {
    "row": 84,
    "rowsha": "Oj+E8Bnc8SOb3yy/mdlOhglbBFKMk1QpUHKEJLyNghs=",
    "originContent": "  username              At least one or more usernames to download stories",
    "translatedContent": "  username              At least one or more usernames to download stories"
  },
  {
    "row": 85,
    "rowsha": "SxNedpSAXJvQzB7u5Y4J7/qknN+wJI7st5DQFpqhzW0=",
    "originContent": "                        for.",
    "translatedContent": "                        for."
  },
  {
    "row": 86,
    "rowsha": "47DEQpj8HBSa+/TImW+5JCeuQeRkm5NMpJWZG3hSuFU=",
    "originContent": "",
    "translatedContent": ""
  },
  {
    "row": 87,
    "rowsha": "32XlRrxXV32ZWwgnoGyJBkmVXUm6Hl6Qz6XsGg6Tomg=",
    "originContent": "optional arguments:",
    "translatedContent": "optional arguments:"
  },
  {
    "row": 88,
    "rowsha": "Oyu3AhN8A0G0Zoh6z/rFKUnhbT8d+SKxzTGxF5pIhN8=",
    "originContent": "  -h, --help            show this help message and exit",
    "translatedContent": "  -h, --help            show this help message and exit"
  },
  {
    "row": 89,
    "rowsha": "XJ7Gy8HbX4tIYs4r9v6Xd3l+dAFQgoV5hpFiAQ5vywQ=",
    "originContent": "  -c, --scan-clipboard  Scan clipboard for story links",
    "translatedContent": "  -c, --scan-clipboard  Scan clipboard for story links"
  },
  {
    "row": 90,
    "rowsha": "pOVlB/Uj0RxayATnDbs1QzCRIql/6TvdGMByZD+UStU=",
    "originContent": "                        ('https://story.snapchat.com/<s>/<username>').",
    "translatedContent": "                        ('https://story.snapchat.com/<s>/<username>')."
  },
  {
    "row": 91,
    "rowsha": "K6HvpzAiSzkVTnwG5NR3QyCkSQbhiEtfciwR8fVahsg=",
    "originContent": "  -u, --check-for-update",
    "translatedContent": "  -u, --check-for-update"
  },
  {
    "row": 92,
    "rowsha": "GOOWA+jULojdy4uq0tVNQP2qKvyleAa7xeG9W6CQriI=",
    "originContent": "                        Periodically check for new stories.",
    "translatedContent": "                        Periodically check for new stories."
  },
  {
    "row": 93,
    "rowsha": "h9yovu0pBIscM1dv1LlJxoB55soLVDoQC/1vaMV5hKw=",
    "originContent": "  -i BATCH_FILENAME, --batch-file BATCH_FILENAME",
    "translatedContent": "  -i BATCH_FILENAME, --batch-file BATCH_FILENAME"
  },
  {
    "row": 94,
    "rowsha": "nVF5lx2JiEU2p3IvFJSB+R9ycUL2tpQrmayTT7BNxts=",
    "originContent": "                        Read usernames from batch file (one username per",
    "translatedContent": "                        Read usernames from batch file (one username per"
  },
  {
    "row": 95,
    "rowsha": "jhLGYnAD4UcNg7stWFfpVSnLXcO9j83TgQLzrG8U2dE=",
    "originContent": "                        line).",
    "translatedContent": "                        line)."
  },
  {
    "row": 96,
    "rowsha": "WEU512g7frQGBQdYrSdOmixcjE5AcJRkVWT+6XtDWTQ=",
    "originContent": "  -P DIRECTORY_PREFIX, --directory-prefix DIRECTORY_PREFIX",
    "translatedContent": "  -P DIRECTORY_PREFIX, --directory-prefix DIRECTORY_PREFIX"
  },
  {
    "row": 97,
    "rowsha": "7/dvVCNFTBJNNqkJUSv2m0IEqRPtA6D+tNc99BndM34=",
    "originContent": "                        Location to store downloaded media.",
    "translatedContent": "                        Location to store downloaded media."
  },
  {
    "row": 98,
    "rowsha": "HJL4rvZOyDIsCgGB3NI1B/r7bUqNfh2fjM6OKSAUK9Y=",
    "originContent": "  -s, --scan-from-prefix",
    "translatedContent": "  -s, --scan-from-prefix"
  },
  {
    "row": 99,
    "rowsha": "FMG1xlrHlfnFgbB6xgCHKKYaXEQhCANX9dUzHBCdG9M=",
    "originContent": "                        Scan usernames (as directory name) from prefix",
    "translatedContent": "                        Scan usernames (as directory name) from prefix"
  },
  {
    "row": 100,
    "rowsha": "qdkhwdROgMkDC7HnjpdMl5WzkaPGl2G2lwe6MjYre/E=",
    "originContent": "                        directory.",
    "translatedContent": "                        directory."
  },
  {
    "row": 101,
    "rowsha": "iUosZAJJ0LdDhQmQOmavJuc7z9JxlUw7araOgqE9dy8=",
    "originContent": "  -d, --dump-json       Save metadata to a JSON file next to downloaded",
    "translatedContent": "  -d, --dump-json       Save metadata to a JSON file next to downloaded"
  },
  {
    "row": 102,
    "rowsha": "Mxk6e2bz5uKADmdgZRnHfqcmJicxI/nMDHmjyr0LP8E=",
    "originContent": "                        videos/pictures.",
    "translatedContent": "                        videos/pictures."
  },
  {
    "row": 103,
    "rowsha": "QDFnFE82xSAgEmYocsS60tLl2+qViiVWoQfvzCjtIMI=",
    "originContent": "  -l MAX_NUM_STORY, --limit-story MAX_NUM_STORY",
    "translatedContent": "  -l MAX_NUM_STORY, --limit-story MAX_NUM_STORY"
  },
  {
    "row": 104,
    "rowsha": "f8VrIZ2wvBgz5seXLpKshVVWGBMRl/iLdqx5orXck8U=",
    "originContent": "                        Set maximum number of stories to download.",
    "translatedContent": "                        Set maximum number of stories to download."
  },
  {
    "row": 105,
    "rowsha": "X0HvQ3fr6ftXdQYSs3COdo+8QVcsez8vXZSFKtoxU80=",
    "originContent": "  -j MAX_WORKERS, --max-concurrent-downloads MAX_WORKERS",
    "translatedContent": "  -j MAX_WORKERS, --max-concurrent-downloads MAX_WORKERS"
  },
  {
    "row": 106,
    "rowsha": "gRPDMlhTjHmDpOpMbP8VHM8Q2AZTyjlzZ2oOA676ZP0=",
    "originContent": "                        Set maximum number of parallel downloads.",
    "translatedContent": "                        Set maximum number of parallel downloads."
  },
  {
    "row": 107,
    "rowsha": "Kva7h0RUNgLDanLL2UyUEnceqNSn54bRE9Hz7IYjvwc=",
    "originContent": "  -t INTERVAL, --update-interval INTERVAL",
    "translatedContent": "  -t INTERVAL, --update-interval INTERVAL"
  },
  {
    "row": 108,
    "rowsha": "u1lPrWKNO7KMBcwv3klCM0lDwYThPTZC2Z9W2sIYssg=",
    "originContent": "                        Set the update interval for checking new story in",
    "translatedContent": "                        Set the update interval for checking new story in"
  },
  {
    "row": 109,
    "rowsha": "AusSg8rAhT5/q7B0+EmZfGVrheb5z3droiZxT3N5lZA=",
    "originContent": "                        seconds. (Default: 10m)",
    "translatedContent": "                        seconds. (Default: 10m)"
  },
  {
    "row": 110,
    "rowsha": "TSpSSYMx32W/tNeqQJUjnUY/Gb9gXMcZwR80NyaoaLQ=",
    "originContent": "  --sleep-interval INTERVAL",
    "translatedContent": "  --sleep-interval INTERVAL"
  },
  {
    "row": 111,
    "rowsha": "n0NdPj/RPyzTtgyOmPuVQOY+jd4muBXBHGMoOfNn32g=",
    "originContent": "                        Sleep between downloads in seconds. (Default: 1s)",
    "translatedContent": "                        Sleep between downloads in seconds. (Default: 1s)"
  },
  {
    "row": 112,
    "rowsha": "+k/YIysynmnM6+Uj6wnPZkFKpb3Fs3TBJdWe66PMQ4s=",
    "originContent": "  -q, --quiet           Do not print anything except errors to the console.",
    "translatedContent": "  -q, --quiet           Do not print anything except errors to the console."
  },
  {
    "row": 113,
    "rowsha": "47DEQpj8HBSa+/TImW+5JCeuQeRkm5NMpJWZG3hSuFU=",
    "originContent": "",
    "translatedContent": ""
  },
  {
    "row": 114,
    "rowsha": "8bkBhHOQsO1+N058HkZOwXtGpCfEh6WtbL0pBkBQg9U=",
    "originContent": "```",
    "translatedContent": "```"
  },
  {
    "row": 115,
    "rowsha": "47DEQpj8HBSa+/TImW+5JCeuQeRkm5NMpJWZG3hSuFU=",
    "originContent": "",
    "translatedContent": ""
  }
]